{
    "DesignerCustomizationType": "Discovery Framework",
    "DiscoveryFrameworkUsageType": "Default",
    "IsActive": true,
    "IsOmniScriptEmbeddable": true,
    "Name": "NZCDCHGRI__GRI416U1Da",
    "OmniProcessId": {
        "Name": "GRI406",
        "VlocityDataPackType": "VlocityMatchingKeyObject",
        "VlocityMatchingRecordSourceKey": "OmniProcess/GRI406/GRI406/English",
        "VlocityRecordSObjectType": "OmniProcess"
    },
    "ParentElementId": {
        "Name": "GRI416",
        "OmniProcessId": {
            "Name": "GRI406",
            "VlocityDataPackType": "VlocityMatchingKeyObject",
            "VlocityMatchingRecordSourceKey": "OmniProcess/GRI406/GRI406/English",
            "VlocityRecordSObjectType": "OmniProcess"
        },
        "VlocityDataPackType": "VlocityMatchingKeyObject",
        "VlocityMatchingRecordSourceKey": "OmniProcessElement/OmniProcess/GRI406/GRI406/English/GRI416",
        "VlocityRecordSObjectType": "OmniProcessElement"
    },
    "ParentElementName": "GRI416",
    "ParentElementType": "Step",
    "PropertySetConfig": {
        "HTMLTemplateId": "",
        "accessibleInFutureSteps": false,
        "conditionType": "Hide if False",
        "controlWidth": 12,
        "debounceValue": 0,
        "defaultValue": null,
        "disOnTplt": false,
        "help": true,
        "helpText": "Percentage of significant product and service categories for which health and safety impacts are assessed for improvement.",
        "helpTextPos": "top-right",
        "hide": false,
        "inputWidth": 12,
        "label": "(416-1a) Percentage of significant product and service categories for which health and safety impacts are assessed for improvement.",
        "mask": null,
        "pattern": "",
        "placeholder": "",
        "ptrnErrText": "",
        "readOnly": false,
        "repeat": false,
        "repeatClone": false,
        "repeatLimit": null,
        "required": false,
        "show": null,
        "showInputWidth": false
    },
    "Type": "Number",
    "VlocityDataPackType": "SObject",
    "VlocityRecordSObjectType": "OmniProcessElement",
    "VlocityRecordSourceKey": "OmniProcessElement/OmniProcess/GRI406/GRI406/English/NZCDCHGRI__GRI416U1Da"
}