{
    "IsActive": true,
    "IsOmniScriptEmbeddable": false,
    "Name": "StartdateEnddate",
    "OmniProcessId": {
        "Name": "GRI2023",
        "VlocityDataPackType": "VlocityMatchingKeyObject",
        "VlocityMatchingRecordSourceKey": "OmniProcess/GRI2023/GRI2023DF/English",
        "VlocityRecordSObjectType": "OmniProcess"
    },
    "PropertySetConfig": {
        "HTMLTemplateId": "",
        "businessCategory": "",
        "businessEvent": "",
        "controlWidth": 12,
        "enableActionMessage": false,
        "enableDefaultAbort": false,
        "errorMessage": {
            "custom": [
            ],
            "default": null
        },
        "extraPayload": {
        },
        "failureAbortLabel": "Abort",
        "failureAbortMessage": "Are you sure?",
        "failureGoBackLabel": "Go Back",
        "failureNextLabel": "Continue",
        "inProgressMessage": "In Progress",
        "integrationProcedureKey": "GRIstartdate_enddate",
        "label": "StartdateEnddate",
        "message": {
        },
        "postMessage": "Done",
        "postTransformBundle": "",
        "preTransformBundle": "",
        "pubsub": false,
        "redirectNextLabel": "Next",
        "redirectNextWidth": 3,
        "redirectPageName": "",
        "redirectPreviousLabel": "Previous",
        "redirectPreviousWidth": 3,
        "redirectTemplateUrl": "vlcAcknowledge.html",
        "remoteOptions": {
            "chainable": false,
            "postTransformBundle": "",
            "preTransformBundle": "",
            "useFuture": false
        },
        "remoteTimeout": 30000,
        "responseJSONNode": "",
        "responseJSONPath": "Response",
        "sendJSONNode": "",
        "sendJSONPath": "",
        "show": null,
        "showPersistentComponent": [
            true,
            false
        ],
        "ssm": false,
        "svgIcon": "",
        "svgSprite": "",
        "useContinuation": false,
        "validationRequired": "Step",
        "wpm": false
    },
    "Type": "Integration Procedure Action",
    "VlocityDataPackType": "SObject",
    "VlocityRecordSObjectType": "OmniProcessElement",
    "VlocityRecordSourceKey": "OmniProcessElement/OmniProcess/GRI2023/GRI2023DF/English/StartdateEnddate"
}