[
    {
        "FilterGroup": 0,
        "GlobalKey": "GRI416U2DaDRCustom5432",
        "InputFieldName": "GRI416U2Da:PenaltyType",
        "InputObjectQuerySequence": 0,
        "IsDisabled": false,
        "IsRequiredForUpsert": false,
        "IsUpsertKey": false,
        "LinkedObjectSequence": 0,
        "Name": "GRI416U2DaDR",
        "OmniDataTransformationId": {
            "Name": "GRI416U2DaDR",
            "VlocityDataPackType": "VlocityMatchingKeyObject",
            "VlocityMatchingRecordSourceKey": "OmniDataTransform/GRI416U2DaDR",
            "VlocityRecordSObjectType": "OmniDataTransform"
        },
        "OutputCreationSequence": 1,
        "OutputFieldName": "NZCDCHGRI__GRI416U2Da:NZCDCHGRI__GRI416U2DaDi",
        "OutputObjectName": "json",
        "VlocityDataPackType": "SObject",
        "VlocityRecordSObjectType": "OmniDataTransformItem"
    },
    {
        "FilterGroup": 0,
        "GlobalKey": "GRI416U2DaDRCustom8264",
        "InputFieldName": "GRI416U2Da:SumIncidentCount",
        "InputObjectQuerySequence": 0,
        "IsDisabled": false,
        "IsRequiredForUpsert": false,
        "IsUpsertKey": false,
        "LinkedObjectSequence": 0,
        "Name": "GRI416U2DaDR",
        "OmniDataTransformationId": {
            "Name": "GRI416U2DaDR",
            "VlocityDataPackType": "VlocityMatchingKeyObject",
            "VlocityMatchingRecordSourceKey": "OmniDataTransform/GRI416U2DaDR",
            "VlocityRecordSObjectType": "OmniDataTransform"
        },
        "OutputCreationSequence": 1,
        "OutputFieldName": "NZCDCHGRI__GRI416U2Da:NZCDCHGRI__GRI416U2DaDii",
        "OutputObjectName": "json",
        "VlocityDataPackType": "SObject",
        "VlocityRecordSObjectType": "OmniDataTransformItem"
    }
]