{
    "DesignerCustomizationType": "Discovery Framework",
    "DiscoveryFrameworkUsageType": "Default",
    "IsActive": true,
    "IsOmniScriptEmbeddable": true,
    "Name": "NZCDCHGRI__GRI306U4DaDiv",
    "OmniProcessId": {
        "Name": "GRI306",
        "VlocityDataPackType": "VlocityMatchingKeyObject",
        "VlocityMatchingRecordSourceKey": "OmniProcess/GRI306/GRI306/English",
        "VlocityRecordSObjectType": "OmniProcess"
    },
    "ParentElementId": {
        "Name": "NZCDCHGRI__GRI306U4Da",
        "OmniProcessId": {
            "Name": "GRI306",
            "VlocityDataPackType": "VlocityMatchingKeyObject",
            "VlocityMatchingRecordSourceKey": "OmniProcess/GRI306/GRI306/English",
            "VlocityRecordSObjectType": "OmniProcess"
        },
        "VlocityDataPackType": "VlocityMatchingKeyObject",
        "VlocityMatchingRecordSourceKey": "OmniProcessElement/OmniProcess/GRI306/GRI306/English/NZCDCHGRI__GRI306U4Da",
        "VlocityRecordSObjectType": "OmniProcessElement"
    },
    "ParentElementName": "NZCDCHGRI__GRI306U4Da",
    "ParentElementType": "Edit Block",
    "PropertySetConfig": {
        "HTMLTemplateId": "",
        "accessibleInFutureSteps": false,
        "conditionType": "Hide if False",
        "controlWidth": 12,
        "controllingField": {
            "element": "",
            "source": "",
            "type": ""
        },
        "defaultValue": null,
        "disOnTplt": true,
        "help": false,
        "helpText": "",
        "hide": false,
        "inputWidth": 12,
        "label": "iv. Disposal Site Type",
        "optionSource": {
            "source": "",
            "type": ""
        },
        "options": [
            {
                "autoAdv": null,
                "name": "Offsite",
                "value": "Offsite"
            },
            {
                "autoAdv": null,
                "name": "Onsite",
                "value": "Onsite"
            }
        ],
        "readOnly": false,
        "repeat": false,
        "repeatClone": false,
        "repeatLimit": null,
        "required": false,
        "show": null,
        "showInputWidth": false
    },
    "Type": "Select",
    "VlocityDataPackType": "SObject",
    "VlocityRecordSObjectType": "OmniProcessElement",
    "VlocityRecordSourceKey": "OmniProcessElement/OmniProcess/GRI306/GRI306/English/NZCDCHGRI__GRI306U4DaDiv"
}