{
    "DiscoveryFrameworkUsageType": "Default",
    "IsActive": true,
    "IsOmniScriptEmbeddable": true,
    "Name": "CustomLWC1",
    "OmniProcessId": {
        "Name": "GRI301",
        "VlocityDataPackType": "VlocityMatchingKeyObject",
        "VlocityMatchingRecordSourceKey": "OmniProcess/GRI301/GRI301/English",
        "VlocityRecordSObjectType": "OmniProcess"
    },
    "ParentElementId": {
        "Name": "Guidance302",
        "OmniProcessId": {
            "Name": "GRI301",
            "VlocityDataPackType": "VlocityMatchingKeyObject",
            "VlocityMatchingRecordSourceKey": "OmniProcess/GRI301/GRI301/English",
            "VlocityRecordSObjectType": "OmniProcess"
        },
        "VlocityDataPackType": "VlocityMatchingKeyObject",
        "VlocityMatchingRecordSourceKey": "OmniProcessElement/OmniProcess/GRI301/GRI301/English/Guidance302",
        "VlocityRecordSObjectType": "OmniProcessElement"
    },
    "ParentElementName": "Guidance302",
    "ParentElementType": "Block",
    "PropertySetConfig": {
        "bStandalone": true,
        "conditionType": "Hide if False",
        "controlWidth": 12,
        "customAttributes": [
        ],
        "hide": false,
        "label": "CustomLWC1",
        "lwcName": "cfGRI302FC",
        "show": null
    },
    "Type": "Custom Lightning Web Component",
    "VlocityDataPackType": "SObject",
    "VlocityRecordSObjectType": "OmniProcessElement",
    "VlocityRecordSourceKey": "OmniProcessElement/OmniProcess/GRI301/GRI301/English/CustomLWC1"
}